<?xml version="1.0"?>
<PaymentFields xmlns:xsi="http://www.w3.org/2001/XMLSchema-instance" xmlns:xsd="http://www.w3.org/2001/XMLSchema">
  <amount>20</amount>
  <approveamount>20</approveamount>
  <authcode>873558</authcode>
  <cardnumber>457889**1028</cardnumber>
  <clientname>GAREGIN HAMBARDZUMYAN</clientname>
  <currency>051</currency>
  <datetime>10.03.2018 13:38:04</datetime>
  <depositamount>20</depositamount>
  <descr>Approved.: - Վճարման ավտորիզացումը կատարված է:</descr>
  <merchantid>19003087</merchantid>
  <opaque>Opaque832</opaque>
  <orderid>832</orderid>
  <orderstatuscode>2</orderstatuscode>
  <payment_state>payment_deposited</payment_state>
  <paymenttype>5</paymenttype>
  <refundamount>0</refundamount>
  <respcode>00</respcode>
  <rewardpoint>0</rewardpoint>
  <rrn>c7afddbe-3225-4b21-9f00-6e4bb5450449</rrn>
  <terminalid>19533087</terminalid>
  <trxnDetails>Bonus Market</trxnDetails>
</PaymentFields>